statax/__init__.py
statax/bootstrap/BCBootstrapper.py
statax/bootstrap/BCaBootstrapper.py
statax/bootstrap/BasicBootstrap.py
statax/bootstrap/Bootstrapper.py
statax/bootstrap/PercentileBootstrapper.py
statax/bootstrap/StandardBootstrapper.py
statax/bootstrap/TBootstrapper.py
statax/bootstrap/__init__.py
statax/bootstrap/types/CIType.py
statax/bootstrap/types/__init__.py
statax/jackknife/JackKnife.py
statax/jackknife/__init__.py
statax-0.3.2.dist-info/METADATA
statax-0.3.2.dist-info/WHEEL
statax-0.3.2.dist-info/licenses/LICENSE
statax-0.3.2.dist-info/RECORD
