Metadata-Version: 2.4
Name: statax
Version: 0.3.2
Summary: A statistical computing library implemented in JAX.
Author-email: Jack Norrie <jack.norrie.dev@gmail.com>
Maintainer-email: Jack Norrie <jack.norrie.dev@gmail.com>
License-Expression: MIT
License-File: LICENSE
Keywords: JAX,bootstrap,statax,statistics
Requires-Python: >=3.11
Requires-Dist: jax[cuda12]<=4.38
